pyabc2/__init__.py
pyabc2/_util.py
pyabc2/key.py
pyabc2/note.py
pyabc2/parse.py
pyabc2/pitch.py
pyabc2/py.typed
pyabc2/abcjs/headless/__init__.py
pyabc2/abcjs/headless/cli.cjs
pyabc2/abcjs/headless/package.json
pyabc2/abcjs/headless/render.js
pyabc2/abcjs/htmlgen/__init__.py
pyabc2/abcjs/widget/__init__.py
pyabc2/abcjs/widget/index.css
pyabc2/abcjs/widget/index.js
pyabc2/sources/__init__.py
pyabc2/sources/_lzstring.py
pyabc2/sources/bill_black.py
pyabc2/sources/bill_black_tunefolders.py
pyabc2/sources/eskin.py
pyabc2/sources/norbeck.py
pyabc2/sources/the_session.py
pyabc2-0.1.1.dist-info/LICENSE
pyabc2-0.1.1.dist-info/WHEEL
pyabc2-0.1.1.dist-info/METADATA
pyabc2-0.1.1.dist-info/RECORD
