Metadata-Version: 2.3
Name: pyabc2
Version: 0.1.1
Summary: Python ABC notation tools
Author-email: zmoon <zmoon92@gmail.com>
Requires-Python: >=3.10,<4
Classifier: License :: OSI Approved :: MIT License
Requires-Dist: cairosvg ; extra == "abcjs-headless"
Requires-Dist: nodejs-wheel-binaries ; extra == "abcjs-headless"
Requires-Dist: anywidget ; extra == "abcjs-widget"
Requires-Dist: ipywidgets ; extra == "abcjs-widget"
Requires-Dist: traitlets ; extra == "abcjs-widget"
Requires-Dist: anywidget[dev] ; extra == "dev"
Requires-Dist: ipython ; extra == "dev"
Requires-Dist: jupyterlab ; extra == "dev"
Requires-Dist: furo ; extra == "doc"
Requires-Dist: matplotlib ; extra == "doc"
Requires-Dist: myst-nb ; extra == "doc"
Requires-Dist: sphinx ==8.* ; extra == "doc"
Requires-Dist: sphinx-copybutton ; extra == "doc"
Requires-Dist: sphinx-inline-tabs ; extra == "doc"
Requires-Dist: numpy ==2.* ; extra == "sources"
Requires-Dist: pandas ==2.* ; extra == "sources"
Requires-Dist: requests ==2.* ; extra == "sources"
Requires-Dist: mypy ; extra == "test"
Requires-Dist: pandas-stubs ==2.* ; extra == "test"
Requires-Dist: pytest ; extra == "test"
Requires-Dist: pytest-cov ; extra == "test"
Requires-Dist: pytest-xdist ; extra == "test"
Project-URL: Documentation, https://pyabc2.readthedocs.io
Project-URL: Home, https://github.com/zmoon/PyABC2
Project-URL: Source, https://github.com/zmoon/PyABC2
Provides-Extra: abcjs-headless
Provides-Extra: abcjs-widget
Provides-Extra: dev
Provides-Extra: doc
Provides-Extra: sources
Provides-Extra: test
